brickie/__init__.py
brickie/bundle.py
brickie/cli.py
brickie/dev.py
brickie/env.py
brickie/serve.py
brickie/assets/spinner.css
brickie/client/__init__.py
brickie/client/esm.py
brickie/client/html.py
brickie/client/react.py
brickie/client/reloader.py
brickie/client/router.py
brickie/client/style.py
brickie/client/style.pyi
js/__init__.py
pyodide/__init__.py
pyodide/ffi/__init__.py
pyodide/ffi/wrappers.py
brickie-0.0.2.dist-info/METADATA
brickie-0.0.2.dist-info/WHEEL
brickie-0.0.2.dist-info/entry_points.txt
brickie-0.0.2.dist-info/licenses/LICENSE
brickie-0.0.2.dist-info/licenses/NOTICE
brickie-0.0.2.dist-info/RECORD
